{
  "reportDir": "/home/runner/workspace/scripts/reports/rayreplica-signal-options-sweeps/2026-05-17T20-11-31-440Z",
  "deployment": {
    "id": "7e2e4e6f-749f-4e65-a011-87d3559a23b0",
    "name": "RayReplica Signal Options Shadow Paper",
    "mode": "paper",
    "symbolUniverse": [
      "SPY",
      "NVDA",
      "DIA",
      "AAPL",
      "MSFT",
      "TSLA",
      "TQQQ",
      "SQQQ",
      "PLTR",
      "COIN",
      "HOOD",
      "RBLX",
      "RKLB",
      "SMCI",
      "VXX",
      "VIXY",
      "TLT",
      "IEF",
      "UUP",
      "GLD",
      "USO",
      "AMZN",
      "META",
      "GOOGL",
      "CRWV",
      "VRT",
      "ALAB",
      "CRDO",
      "COHR",
      "LITE",
      "AAOI",
      "FN",
      "CIEN",
      "CLS",
      "DELL",
      "APH",
      "GLW",
      "RTX",
      "LMT",
      "NOC",
      "GD",
      "LHX",
      "KTOS",
      "AVAV",
      "TDY",
      "HEI",
      "TDG",
      "BAH",
      "ESLT",
      "LUNR",
      "JOBY",
      "ACHR",
      "GEV",
      "CEG",
      "VST",
      "TLN",
      "NRG",
      "OKLO",
      "CCJ",
      "UUUU",
      "BWXT",
      "ETN",
      "PWR",
      "POWL",
      "IONQ",
      "RGTI",
      "QBTS",
      "MSTR",
      "APLD",
      "CLSK",
      "HUT",
      "CORZ",
      "OUST",
      "SYM",
      "AMBA",
      "CGNX",
      "ZBRA",
      "ISRG",
      "ROK",
      "AMD",
      "AVGO",
      "TSM",
      "MU",
      "QCOM",
      "ARM",
      "SOXX",
      "SMH",
      "ASML",
      "MRVL",
      "ANET"
    ]
  },
  "config": {
    "start": "2026-05-04",
    "end": "2026-05-05",
    "session": "regular",
    "signalTimeframe": "5m",
    "smoke": true,
    "replayWinner": false,
    "lockWaitMs": 300000,
    "reportDir": "/home/runner/workspace/scripts/reports/rayreplica-signal-options-sweeps/2026-05-17T20-11-31-440Z"
  },
  "results": [
    {
      "variant": {
        "id": "stage-a-h4",
        "stage": "A",
        "rayReplicaSettingsPatch": {
          "timeHorizon": 4
        }
      },
      "status": "succeeded",
      "eligible": false,
      "ineligibleReason": "closed trades below 20",
      "startedAt": "2026-05-17T20:14:56.577Z",
      "finishedAt": "2026-05-17T20:17:29.015Z",
      "durationMs": 152438,
      "window": {
        "start": "2026-05-04",
        "end": "2026-05-05",
        "session": "regular",
        "from": "2026-05-04T00:00:00.000Z",
        "to": "2026-05-05T23:59:59.999Z"
      },
      "timeframe": "5m",
      "metrics": {
        "realizedPnl": 944,
        "winRate": 0.8,
        "profitFactor": 17.857142857142858,
        "closedTrades": 15,
        "maxDrawdownAbs": 0,
        "openPositions": 3,
        "riskAdjustedScore": 1.888
      },
      "summary": {
        "symbolsEvaluated": 90,
        "symbolUniverse": {
          "source": "deployment",
          "symbols": [
            "SPY",
            "NVDA",
            "DIA",
            "AAPL",
            "MSFT",
            "TSLA",
            "TQQQ",
            "SQQQ",
            "PLTR",
            "COIN",
            "HOOD",
            "RBLX",
            "RKLB",
            "SMCI",
            "VXX",
            "VIXY",
            "TLT",
            "IEF",
            "UUP",
            "GLD",
            "USO",
            "AMZN",
            "META",
            "GOOGL",
            "CRWV",
            "VRT",
            "ALAB",
            "CRDO",
            "COHR",
            "LITE",
            "AAOI",
            "FN",
            "CIEN",
            "CLS",
            "DELL",
            "APH",
            "GLW",
            "RTX",
            "LMT",
            "NOC",
            "GD",
            "LHX",
            "KTOS",
            "AVAV",
            "TDY",
            "HEI",
            "TDG",
            "BAH",
            "ESLT",
            "LUNR",
            "JOBY",
            "ACHR",
            "GEV",
            "CEG",
            "VST",
            "TLN",
            "NRG",
            "OKLO",
            "CCJ",
            "UUUU",
            "BWXT",
            "ETN",
            "PWR",
            "POWL",
            "IONQ",
            "RGTI",
            "QBTS",
            "MSTR",
            "APLD",
            "CLSK",
            "HUT",
            "CORZ",
            "OUST",
            "SYM",
            "AMBA",
            "CGNX",
            "ZBRA",
            "ISRG",
            "ROK",
            "AMD",
            "AVGO",
            "TSM",
            "MU",
            "QCOM",
            "ARM",
            "SOXX",
            "SMH",
            "ASML",
            "MRVL",
            "ANET"
          ],
          "watchlistId": null,
          "skippedSymbols": [],
          "truncated": false
        },
        "signalsEvaluated": 385,
        "entriesOpened": 18,
        "exitsClosed": 15,
        "marksRecorded": 1264,
        "candidatesSkipped": 325,
        "existingEvents": 42,
        "mirrorRepairsAttempted": 0,
        "missingOptionBars": 70,
        "realizedPnl": 944,
        "winningTrades": 12,
        "losingTrades": 3,
        "exitReasons": {
          "opposite_signal": 9,
          "runner_trail_stop": 5,
          "expiration": 1
        },
        "skippedReasons": {
          "historical_option_bars_unavailable": 70,
          "mtf_not_aligned": 179,
          "inverse_put_blocked": 2,
          "max_open_symbols_reached": 74
        },
        "closedTrades": [
          {
            "candidateId": "SIGOPT-7e2e4e6f-SPY-buy-1777903500000",
            "symbol": "SPY",
            "direction": "buy",
            "optionRight": "call",
            "openedAt": "2026-05-04T14:05:00.000Z",
            "closedAt": "2026-05-04T15:15:00.000Z",
            "entryPrice": 3.75,
            "exitPrice": 3.83,
            "quantity": 1,
            "pnl": 8,
            "reason": "opposite_signal",
            "selectedContract": {
              "ticker": "O:SPY260505C00718000",
              "underlying": "SPY",
              "expirationDate": "2026-05-05",
              "strike": 718,
              "right": "call",
              "multiplier": 100,
              "sharesPerContract": 100,
              "providerContractId": "O:SPY260505C00718000"
            }
          },
          {
            "candidateId": "SIGOPT-7e2e4e6f-USO-buy-1777906200000",
            "symbol": "USO",
            "direction": "buy",
            "optionRight": "call",
            "openedAt": "2026-05-04T14:54:00.000Z",
            "closedAt": "2026-05-04T18:00:00.000Z",
            "entryPrice": 4.25,
            "exitPrice": 6.9,
            "quantity": 1,
            "pnl": 265,
            "reason": "opposite_signal",
            "selectedContract": {
              "ticker": "O:USO260506C00143000",
              "underlying": "USO",
              "expirationDate": "2026-05-06",
              "strike": 143,
              "right": "call",
              "multiplier": 100,
              "sharesPerContract": 100,
              "providerContractId": "O:USO260506C00143000"
            }
          },
          {
            "candidateId": "SIGOPT-7e2e4e6f-AAPL-buy-1777914600000",
            "symbol": "AAPL",
            "direction": "buy",
            "optionRight": "call",
            "openedAt": "2026-05-04T17:11:00.000Z",
            "closedAt": "2026-05-04T18:30:00.000Z",
            "entryPrice": 3.48,
            "exitPrice": 3.25,
            "quantity": 1,
            "pnl": -23,
            "reason": "opposite_signal",
            "selectedContract": {
              "ticker": "O:AAPL260506C00275000",
              "underlying": "AAPL",
              "expirationDate": "2026-05-06",
              "strike": 275,
              "right": "call",
              "multiplier": 100,
              "sharesPerContract": 100,
              "providerContractId": "O:AAPL260506C00275000"
            }
          },
          {
            "candidateId": "SIGOPT-7e2e4e6f-GOOGL-buy-1777909800000",
            "symbol": "GOOGL",
            "direction": "buy",
            "optionRight": "call",
            "openedAt": "2026-05-04T15:50:00.000Z",
            "closedAt": "2026-05-04T18:40:00.000Z",
            "entryPrice": 2.75,
            "exitPrice": 2.85,
            "quantity": 1,
            "pnl": 10,
            "reason": "opposite_signal",
            "selectedContract": {
              "ticker": "O:GOOGL260506C00385000",
              "underlying": "GOOGL",
              "expirationDate": "2026-05-06",
              "strike": 385,
              "right": "call",
              "multiplier": 100,
              "sharesPerContract": 100,
              "providerContractId": "O:GOOGL260506C00385000"
            }
          },
          {
            "candidateId": "SIGOPT-7e2e4e6f-NVDA-buy-1777912500000",
            "symbol": "NVDA",
            "direction": "buy",
            "optionRight": "call",
            "openedAt": "2026-05-04T16:35:00.000Z",
            "closedAt": "2026-05-04T18:44:00.000Z",
            "entryPrice": 3.37,
            "exitPrice": 3.88,
            "quantity": 1,
            "pnl": 51,
            "reason": "runner_trail_stop",
            "selectedContract": {
              "ticker": "O:NVDA260506C00195000",
              "underlying": "NVDA",
              "expirationDate": "2026-05-06",
              "strike": 195,
              "right": "call",
              "multiplier": 100,
              "sharesPerContract": 100,
              "providerContractId": "O:NVDA260506C00195000"
            }
          },
          {
            "candidateId": "SIGOPT-7e2e4e6f-SPY-buy-1777914600000",
            "symbol": "SPY",
            "direction": "buy",
            "optionRight": "call",
            "openedAt": "2026-05-04T17:10:00.000Z",
            "closedAt": "2026-05-05T13:30:00.000Z",
            "entryPrice": 4.32,
            "exitPrice": 6.93,
            "quantity": 1,
            "pnl": 261,
            "reason": "expiration",
            "selectedContract": {
              "ticker": "O:SPY260505C00715000",
              "underlying": "SPY",
              "expirationDate": "2026-05-05",
              "strike": 715,
              "right": "call",
              "multiplier": 100,
              "sharesPerContract": 100,
              "providerContractId": "O:SPY260505C00715000"
            }
          },
          {
            "candidateId": "SIGOPT-7e2e4e6f-TLT-buy-1777921500000",
            "symbol": "TLT",
            "direction": "buy",
            "optionRight": "call",
            "openedAt": "2026-05-04T19:05:00.000Z",
            "closedAt": "2026-05-05T14:19:00.000Z",
            "entryPrice": 0.28,
            "exitPrice": 0.33,
            "quantity": 3,
            "pnl": 15,
            "reason": "runner_trail_stop",
            "selectedContract": {
              "ticker": "O:TLT260506C00085000",
              "underlying": "TLT",
              "expirationDate": "2026-05-06",
              "strike": 85,
              "right": "call",
              "multiplier": 100,
              "sharesPerContract": 100,
              "providerContractId": "O:TLT260506C00085000"
            }
          },
          {
            "candidateId": "SIGOPT-7e2e4e6f-AAPL-buy-1777921800000",
            "symbol": "AAPL",
            "direction": "buy",
            "optionRight": "call",
            "openedAt": "2026-05-04T19:11:00.000Z",
            "closedAt": "2026-05-05T14:50:00.000Z",
            "entryPrice": 3.3,
            "exitPrice": 6.2,
            "quantity": 1,
            "pnl": 290,
            "reason": "runner_trail_stop",
            "selectedContract": {
              "ticker": "O:AAPL260506C00275000",
              "underlying": "AAPL",
              "expirationDate": "2026-05-06",
              "strike": 275,
              "right": "call",
              "multiplier": 100,
              "sharesPerContract": 100,
              "providerContractId": "O:AAPL260506C00275000"
            }
          },
          {
            "candidateId": "SIGOPT-7e2e4e6f-IEF-buy-1777989300000",
            "symbol": "IEF",
            "direction": "buy",
            "optionRight": "call",
            "openedAt": "2026-05-05T14:11:00.000Z",
            "closedAt": "2026-05-05T17:05:00.000Z",
            "entryPrice": 0.1,
            "exitPrice": 0.11,
            "quantity": 3,
            "pnl": 3,
            "reason": "opposite_signal",
            "selectedContract": {
              "ticker": "O:IEF260508C00095000",
              "underlying": "IEF",
              "expirationDate": "2026-05-08",
              "strike": 95,
              "right": "call",
              "multiplier": 100,
              "sharesPerContract": 100,
              "providerContractId": "O:IEF260508C00095000"
            }
          },
          {
            "candidateId": "SIGOPT-7e2e4e6f-VXX-buy-1777990200000",
            "symbol": "VXX",
            "direction": "buy",
            "optionRight": "call",
            "openedAt": "2026-05-05T14:10:00.000Z",
            "closedAt": "2026-05-05T17:33:00.000Z",
            "entryPrice": 0.5,
            "exitPrice": 0.56,
            "quantity": 3,
            "pnl": 18,
            "reason": "runner_trail_stop",
            "selectedContract": {
              "ticker": "O:VXX260508C00028000",
              "underlying": "VXX",
              "expirationDate": "2026-05-08",
              "strike": 28,
              "right": "call",
              "multiplier": 100,
              "sharesPerContract": 100,
              "providerContractId": "O:VXX260508C00028000"
            }
          },
          {
            "candidateId": "SIGOPT-7e2e4e6f-AAPL-buy-1778001300000",
            "symbol": "AAPL",
            "direction": "buy",
            "optionRight": "call",
            "openedAt": "2026-05-05T17:15:00.000Z",
            "closedAt": "2026-05-05T17:33:00.000Z",
            "entryPrice": 2.95,
            "exitPrice": 3.55,
            "quantity": 1,
            "pnl": 60,
            "reason": "runner_trail_stop",
            "selectedContract": {
              "ticker": "O:AAPL260506C00280000",
              "underlying": "AAPL",
              "expirationDate": "2026-05-06",
              "strike": 280,
              "right": "call",
              "multiplier": 100,
              "sharesPerContract": 100,
              "providerContractId": "O:AAPL260506C00280000"
            }
          },
          {
            "candidateId": "SIGOPT-7e2e4e6f-OUST-buy-1777993200000",
            "symbol": "OUST",
            "direction": "buy",
            "optionRight": "call",
            "openedAt": "2026-05-05T15:15:00.000Z",
            "closedAt": "2026-05-05T17:35:00.000Z",
            "entryPrice": 2.95,
            "exitPrice": 2.65,
            "quantity": 1,
            "pnl": -30,
            "reason": "opposite_signal",
            "selectedContract": {
              "ticker": "O:OUST260508C00029000",
              "underlying": "OUST",
              "expirationDate": "2026-05-08",
              "strike": 29,
              "right": "call",
              "multiplier": 100,
              "sharesPerContract": 100,
              "providerContractId": "O:OUST260508C00029000"
            }
          },
          {
            "candidateId": "SIGOPT-7e2e4e6f-MSFT-buy-1778002500000",
            "symbol": "MSFT",
            "direction": "buy",
            "optionRight": "call",
            "openedAt": "2026-05-05T17:35:00.000Z",
            "closedAt": "2026-05-05T18:25:00.000Z",
            "entryPrice": 2.96,
            "exitPrice": 3.09,
            "quantity": 1,
            "pnl": 13,
            "reason": "opposite_signal",
            "selectedContract": {
              "ticker": "O:MSFT260506C00410000",
              "underlying": "MSFT",
              "expirationDate": "2026-05-06",
              "strike": 410,
              "right": "call",
              "multiplier": 100,
              "sharesPerContract": 100,
              "providerContractId": "O:MSFT260506C00410000"
            }
          },
          {
            "candidateId": "SIGOPT-7e2e4e6f-TQQQ-buy-1778003100000",
            "symbol": "TQQQ",
            "direction": "buy",
            "optionRight": "call",
            "openedAt": "2026-05-05T17:45:00.000Z",
            "closedAt": "2026-05-05T19:40:00.000Z",
            "entryPrice": 1.29,
            "exitPrice": 1.28,
            "quantity": 3,
            "pnl": -3,
            "reason": "opposite_signal",
            "selectedContract": {
              "ticker": "O:TQQQ260508C00068000",
              "underlying": "TQQQ",
              "expirationDate": "2026-05-08",
              "strike": 68,
              "right": "call",
              "multiplier": 100,
              "sharesPerContract": 100,
              "providerContractId": "O:TQQQ260508C00068000"
            }
          },
          {
            "candidateId": "SIGOPT-7e2e4e6f-AMZN-buy-1778003400000",
            "symbol": "AMZN",
            "direction": "buy",
            "optionRight": "call",
            "openedAt": "2026-05-05T17:50:00.000Z",
            "closedAt": "2026-05-05T19:55:00.000Z",
            "entryPrice": 1.35,
            "exitPrice": 1.37,
            "quantity": 3,
            "pnl": 6,
            "reason": "opposite_signal",
            "selectedContract": {
              "ticker": "O:AMZN260506C00275000",
              "underlying": "AMZN",
              "expirationDate": "2026-05-06",
              "strike": 275,
              "right": "call",
              "multiplier": 100,
              "sharesPerContract": 100,
              "providerContractId": "O:AMZN260506C00275000"
            }
          }
        ],
        "errors": []
      },
      "error": null
    },
    {
      "variant": {
        "id": "stage-a-h6",
        "stage": "A",
        "rayReplicaSettingsPatch": {
          "timeHorizon": 6
        }
      },
      "status": "succeeded",
      "eligible": false,
      "ineligibleReason": "closed trades below 20",
      "startedAt": "2026-05-17T20:17:29.015Z",
      "finishedAt": "2026-05-17T20:19:38.286Z",
      "durationMs": 129271,
      "window": {
        "start": "2026-05-04",
        "end": "2026-05-05",
        "session": "regular",
        "from": "2026-05-04T00:00:00.000Z",
        "to": "2026-05-05T23:59:59.999Z"
      },
      "timeframe": "5m",
      "metrics": {
        "realizedPnl": 1018,
        "winRate": 0.6666666666666666,
        "profitFactor": 11.946236559139784,
        "closedTrades": 12,
        "maxDrawdownAbs": 0,
        "openPositions": 4,
        "riskAdjustedScore": 2.036
      },
      "summary": {
        "symbolsEvaluated": 90,
        "symbolUniverse": {
          "source": "deployment",
          "symbols": [
            "SPY",
            "NVDA",
            "DIA",
            "AAPL",
            "MSFT",
            "TSLA",
            "TQQQ",
            "SQQQ",
            "PLTR",
            "COIN",
            "HOOD",
            "RBLX",
            "RKLB",
            "SMCI",
            "VXX",
            "VIXY",
            "TLT",
            "IEF",
            "UUP",
            "GLD",
            "USO",
            "AMZN",
            "META",
            "GOOGL",
            "CRWV",
            "VRT",
            "ALAB",
            "CRDO",
            "COHR",
            "LITE",
            "AAOI",
            "FN",
            "CIEN",
            "CLS",
            "DELL",
            "APH",
            "GLW",
            "RTX",
            "LMT",
            "NOC",
            "GD",
            "LHX",
            "KTOS",
            "AVAV",
            "TDY",
            "HEI",
            "TDG",
            "BAH",
            "ESLT",
            "LUNR",
            "JOBY",
            "ACHR",
            "GEV",
            "CEG",
            "VST",
            "TLN",
            "NRG",
            "OKLO",
            "CCJ",
            "UUUU",
            "BWXT",
            "ETN",
            "PWR",
            "POWL",
            "IONQ",
            "RGTI",
            "QBTS",
            "MSTR",
            "APLD",
            "CLSK",
            "HUT",
            "CORZ",
            "OUST",
            "SYM",
            "AMBA",
            "CGNX",
            "ZBRA",
            "ISRG",
            "ROK",
            "AMD",
            "AVGO",
            "TSM",
            "MU",
            "QCOM",
            "ARM",
            "SOXX",
            "SMH",
            "ASML",
            "MRVL",
            "ANET"
          ],
          "watchlistId": null,
          "skippedSymbols": [],
          "truncated": false
        },
        "signalsEvaluated": 270,
        "entriesOpened": 16,
        "exitsClosed": 12,
        "marksRecorded": 1059,
        "candidatesSkipped": 200,
        "existingEvents": 54,
        "mirrorRepairsAttempted": 0,
        "missingOptionBars": 55,
        "realizedPnl": 1018,
        "winningTrades": 8,
        "losingTrades": 4,
        "exitReasons": {
          "opposite_signal": 6,
          "expiration": 1,
          "runner_trail_stop": 5
        },
        "skippedReasons": {
          "historical_option_bars_unavailable": 55,
          "mtf_not_aligned": 111,
          "inverse_put_blocked": 1,
          "max_open_symbols_reached": 33
        },
        "closedTrades": [
          {
            "candidateId": "SIGOPT-7e2e4e6f-SPY-buy-1777903500000",
            "symbol": "SPY",
            "direction": "buy",
            "optionRight": "call",
            "openedAt": "2026-05-04T14:05:00.000Z",
            "closedAt": "2026-05-04T15:15:00.000Z",
            "entryPrice": 3.75,
            "exitPrice": 3.83,
            "quantity": 1,
            "pnl": 8,
            "reason": "opposite_signal",
            "selectedContract": {
              "ticker": "O:SPY260505C00718000",
              "underlying": "SPY",
              "expirationDate": "2026-05-05",
              "strike": 718,
              "right": "call",
              "multiplier": 100,
              "sharesPerContract": 100,
              "providerContractId": "O:SPY260505C00718000"
            }
          },
          {
            "candidateId": "SIGOPT-7e2e4e6f-USO-buy-1777906200000",
            "symbol": "USO",
            "direction": "buy",
            "optionRight": "call",
            "openedAt": "2026-05-04T14:54:00.000Z",
            "closedAt": "2026-05-04T18:00:00.000Z",
            "entryPrice": 4.25,
            "exitPrice": 6.9,
            "quantity": 1,
            "pnl": 265,
            "reason": "opposite_signal",
            "selectedContract": {
              "ticker": "O:USO260506C00143000",
              "underlying": "USO",
              "expirationDate": "2026-05-06",
              "strike": 143,
              "right": "call",
              "multiplier": 100,
              "sharesPerContract": 100,
              "providerContractId": "O:USO260506C00143000"
            }
          },
          {
            "candidateId": "SIGOPT-7e2e4e6f-SPY-buy-1777917300000",
            "symbol": "SPY",
            "direction": "buy",
            "optionRight": "call",
            "openedAt": "2026-05-04T17:56:00.000Z",
            "closedAt": "2026-05-05T13:30:00.000Z",
            "entryPrice": 3.35,
            "exitPrice": 5.03,
            "quantity": 1,
            "pnl": 168,
            "reason": "expiration",
            "selectedContract": {
              "ticker": "O:SPY260505C00717000",
              "underlying": "SPY",
              "expirationDate": "2026-05-05",
              "strike": 717,
              "right": "call",
              "multiplier": 100,
              "sharesPerContract": 100,
              "providerContractId": "O:SPY260505C00717000"
            }
          },
          {
            "candidateId": "SIGOPT-7e2e4e6f-GOOGL-buy-1777914600000",
            "symbol": "GOOGL",
            "direction": "buy",
            "optionRight": "call",
            "openedAt": "2026-05-04T17:10:00.000Z",
            "closedAt": "2026-05-05T13:55:00.000Z",
            "entryPrice": 3.1,
            "exitPrice": 5.93,
            "quantity": 1,
            "pnl": 283,
            "reason": "runner_trail_stop",
            "selectedContract": {
              "ticker": "O:GOOGL260506C00385000",
              "underlying": "GOOGL",
              "expirationDate": "2026-05-06",
              "strike": 385,
              "right": "call",
              "multiplier": 100,
              "sharesPerContract": 100,
              "providerContractId": "O:GOOGL260506C00385000"
            }
          },
          {
            "candidateId": "SIGOPT-7e2e4e6f-TLT-buy-1777921500000",
            "symbol": "TLT",
            "direction": "buy",
            "optionRight": "call",
            "openedAt": "2026-05-04T19:05:00.000Z",
            "closedAt": "2026-05-05T14:19:00.000Z",
            "entryPrice": 0.28,
            "exitPrice": 0.33,
            "quantity": 3,
            "pnl": 15,
            "reason": "runner_trail_stop",
            "selectedContract": {
              "ticker": "O:TLT260506C00085000",
              "underlying": "TLT",
              "expirationDate": "2026-05-06",
              "strike": 85,
              "right": "call",
              "multiplier": 100,
              "sharesPerContract": 100,
              "providerContractId": "O:TLT260506C00085000"
            }
          },
          {
            "candidateId": "SIGOPT-7e2e4e6f-AAPL-buy-1777921800000",
            "symbol": "AAPL",
            "direction": "buy",
            "optionRight": "call",
            "openedAt": "2026-05-04T19:11:00.000Z",
            "closedAt": "2026-05-05T14:50:00.000Z",
            "entryPrice": 3.3,
            "exitPrice": 6.2,
            "quantity": 1,
            "pnl": 290,
            "reason": "runner_trail_stop",
            "selectedContract": {
              "ticker": "O:AAPL260506C00275000",
              "underlying": "AAPL",
              "expirationDate": "2026-05-06",
              "strike": 275,
              "right": "call",
              "multiplier": 100,
              "sharesPerContract": 100,
              "providerContractId": "O:AAPL260506C00275000"
            }
          },
          {
            "candidateId": "SIGOPT-7e2e4e6f-GLD-buy-1777990800000",
            "symbol": "GLD",
            "direction": "buy",
            "optionRight": "call",
            "openedAt": "2026-05-05T14:20:00.000Z",
            "closedAt": "2026-05-05T15:55:00.000Z",
            "entryPrice": 2.78,
            "exitPrice": 2.53,
            "quantity": 1,
            "pnl": -25,
            "reason": "opposite_signal",
            "selectedContract": {
              "ticker": "O:GLD260506C00419000",
              "underlying": "GLD",
              "expirationDate": "2026-05-06",
              "strike": 419,
              "right": "call",
              "multiplier": 100,
              "sharesPerContract": 100,
              "providerContractId": "O:GLD260506C00419000"
            }
          },
          {
            "candidateId": "SIGOPT-7e2e4e6f-VXX-buy-1777990200000",
            "symbol": "VXX",
            "direction": "buy",
            "optionRight": "call",
            "openedAt": "2026-05-05T14:10:00.000Z",
            "closedAt": "2026-05-05T17:33:00.000Z",
            "entryPrice": 0.5,
            "exitPrice": 0.56,
            "quantity": 3,
            "pnl": 18,
            "reason": "runner_trail_stop",
            "selectedContract": {
              "ticker": "O:VXX260508C00028000",
              "underlying": "VXX",
              "expirationDate": "2026-05-08",
              "strike": 28,
              "right": "call",
              "multiplier": 100,
              "sharesPerContract": 100,
              "providerContractId": "O:VXX260508C00028000"
            }
          },
          {
            "candidateId": "SIGOPT-7e2e4e6f-OUST-buy-1777993200000",
            "symbol": "OUST",
            "direction": "buy",
            "optionRight": "call",
            "openedAt": "2026-05-05T15:15:00.000Z",
            "closedAt": "2026-05-05T17:35:00.000Z",
            "entryPrice": 2.95,
            "exitPrice": 2.65,
            "quantity": 1,
            "pnl": -30,
            "reason": "opposite_signal",
            "selectedContract": {
              "ticker": "O:OUST260508C00029000",
              "underlying": "OUST",
              "expirationDate": "2026-05-08",
              "strike": 29,
              "right": "call",
              "multiplier": 100,
              "sharesPerContract": 100,
              "providerContractId": "O:OUST260508C00029000"
            }
          },
          {
            "candidateId": "SIGOPT-7e2e4e6f-PLTR-buy-1778004000000",
            "symbol": "PLTR",
            "direction": "buy",
            "optionRight": "call",
            "openedAt": "2026-05-05T18:01:00.000Z",
            "closedAt": "2026-05-05T18:45:00.000Z",
            "entryPrice": 3.83,
            "exitPrice": 3.65,
            "quantity": 1,
            "pnl": -18,
            "reason": "opposite_signal",
            "selectedContract": {
              "ticker": "O:PLTR260508C00135000",
              "underlying": "PLTR",
              "expirationDate": "2026-05-08",
              "strike": 135,
              "right": "call",
              "multiplier": 100,
              "sharesPerContract": 100,
              "providerContractId": "O:PLTR260508C00135000"
            }
          },
          {
            "candidateId": "SIGOPT-7e2e4e6f-NRG-buy-1777996500000",
            "symbol": "NRG",
            "direction": "buy",
            "optionRight": "call",
            "openedAt": "2026-05-05T16:56:00.000Z",
            "closedAt": "2026-05-05T19:00:00.000Z",
            "entryPrice": 4.8,
            "exitPrice": 4.6,
            "quantity": 1,
            "pnl": -20,
            "reason": "opposite_signal",
            "selectedContract": {
              "ticker": "O:NRG260508C00160000",
              "underlying": "NRG",
              "expirationDate": "2026-05-08",
              "strike": 160,
              "right": "call",
              "multiplier": 100,
              "sharesPerContract": 100,
              "providerContractId": "O:NRG260508C00160000"
            }
          },
          {
            "candidateId": "SIGOPT-7e2e4e6f-MSFT-buy-1778002500000",
            "symbol": "MSFT",
            "direction": "buy",
            "optionRight": "call",
            "openedAt": "2026-05-05T17:35:00.000Z",
            "closedAt": "2026-05-05T19:57:00.000Z",
            "entryPrice": 2.96,
            "exitPrice": 3.6,
            "quantity": 1,
            "pnl": 64,
            "reason": "runner_trail_stop",
            "selectedContract": {
              "ticker": "O:MSFT260506C00410000",
              "underlying": "MSFT",
              "expirationDate": "2026-05-06",
              "strike": 410,
              "right": "call",
              "multiplier": 100,
              "sharesPerContract": 100,
              "providerContractId": "O:MSFT260506C00410000"
            }
          }
        ],
        "errors": []
      },
      "error": null
    }
  ],
  "ranked": [],
  "replayResult": null,
  "verification": null
}
